{"expireTime":9007200889669842000,"key":"ab35f5f8ecd56949113ea3a4c1808837","val":{"name":"IMAGE_PROCESSING","inputPaths":["/Users/abuj/Documents/GitHub/ajaye2.github.io/src/images/KIDS4KIDS.png"],"outputDir":"/Users/abuj/Documents/GitHub/ajaye2.github.io/public/static/06eea2815b0c12cb780a19d4e18c9fa6","args":{"isLazy":false,"operations":[{"outputPath":"8ba1e/KIDS4KIDS.png","args":{"height":50,"width":50,"cropFocus":17,"toFormat":"png","fit":"cover","background":"rgba(0,0,0,1)"}},{"outputPath":"71eb7/KIDS4KIDS.png","args":{"height":100,"width":100,"cropFocus":17,"toFormat":"png","fit":"cover","background":"rgba(0,0,0,1)"}},{"outputPath":"b3a76/KIDS4KIDS.png","args":{"height":200,"width":200,"cropFocus":17,"toFormat":"png","fit":"cover","background":"rgba(0,0,0,1)"}},{"outputPath":"56e34/KIDS4KIDS.png","args":{"height":300,"width":300,"cropFocus":17,"toFormat":"png","fit":"cover","background":"rgba(0,0,0,1)"}},{"outputPath":"0a8d8/KIDS4KIDS.png","args":{"height":400,"width":400,"cropFocus":17,"toFormat":"png","fit":"cover","background":"rgba(0,0,0,1)"}},{"outputPath":"65a0f/KIDS4KIDS.png","args":{"height":1470,"width":1470,"cropFocus":17,"toFormat":"png","fit":"cover","background":"rgba(0,0,0,1)"}}],"pluginOptions":{"base64Width":20,"forceBase64Format":"","useMozJpeg":false,"stripMetadata":true,"lazyImageGeneration":true,"defaultQuality":50,"failOnError":true,"plugins":[]}}}}