{"expireTime":9007200889669864000,"key":"a8a757fbb04b3ceeb79ee8c50d20d8dd","val":{"name":"IMAGE_PROCESSING","inputPaths":["/Users/abuj/Documents/GitHub/ajaye2.github.io/src/images/profile.jpg"],"outputDir":"/Users/abuj/Documents/GitHub/ajaye2.github.io/public/static/bc435e424b8e5795b31d6ff685ef3eb7","args":{"isLazy":false,"operations":[{"outputPath":"3d421/profile.jpg","args":{"height":10,"cropFocus":17,"toFormat":"jpg","fit":"cover","background":"rgba(0,0,0,1)"}},{"outputPath":"4d444/profile.jpg","args":{"height":20,"cropFocus":17,"toFormat":"jpg","fit":"cover","background":"rgba(0,0,0,1)"}},{"outputPath":"75150/profile.jpg","args":{"height":40,"cropFocus":17,"toFormat":"jpg","fit":"cover","background":"rgba(0,0,0,1)"}},{"outputPath":"dc601/profile.jpg","args":{"height":60,"cropFocus":17,"toFormat":"jpg","fit":"cover","background":"rgba(0,0,0,1)"}},{"outputPath":"02483/profile.jpg","args":{"height":80,"cropFocus":17,"toFormat":"jpg","fit":"cover","background":"rgba(0,0,0,1)"}},{"outputPath":"887f4/profile.jpg","args":{"height":640,"cropFocus":17,"toFormat":"jpg","fit":"cover","background":"rgba(0,0,0,1)"}}],"pluginOptions":{"base64Width":20,"forceBase64Format":"","useMozJpeg":false,"stripMetadata":true,"lazyImageGeneration":true,"defaultQuality":50,"failOnError":true,"plugins":[]}}}}