{"expireTime":9007200889669842000,"key":"fc7ad438b79bbb692f773bff7625fc45","val":{"name":"IMAGE_PROCESSING","inputPaths":["/Users/abuj/Documents/GitHub/ajaye2.github.io/src/images/LUMNIS Logo.png"],"outputDir":"/Users/abuj/Documents/GitHub/ajaye2.github.io/public/static/f0cae6771761d8249abba5b6447f674e","args":{"isLazy":false,"operations":[{"outputPath":"8ba1e/LUMNIS Logo.png","args":{"height":50,"width":50,"cropFocus":17,"toFormat":"png","fit":"cover","background":"rgba(0,0,0,1)"}},{"outputPath":"71eb7/LUMNIS Logo.png","args":{"height":100,"width":100,"cropFocus":17,"toFormat":"png","fit":"cover","background":"rgba(0,0,0,1)"}},{"outputPath":"b3a76/LUMNIS Logo.png","args":{"height":200,"width":200,"cropFocus":17,"toFormat":"png","fit":"cover","background":"rgba(0,0,0,1)"}},{"outputPath":"56e34/LUMNIS Logo.png","args":{"height":300,"width":300,"cropFocus":17,"toFormat":"png","fit":"cover","background":"rgba(0,0,0,1)"}},{"outputPath":"b8abe/LUMNIS Logo.png","args":{"height":320,"width":320,"cropFocus":17,"toFormat":"png","fit":"cover","background":"rgba(0,0,0,1)"}}],"pluginOptions":{"base64Width":20,"forceBase64Format":"","useMozJpeg":false,"stripMetadata":true,"lazyImageGeneration":true,"defaultQuality":50,"failOnError":true,"plugins":[]}}}}